acdh_cidoc_pyutils/__init__.py
acdh_cidoc_pyutils/namespaces.py
acdh_cidoc_pyutils/utils.py
acdh_cidoc_pyutils-1.12.1.dist-info/METADATA
acdh_cidoc_pyutils-1.12.1.dist-info/WHEEL
acdh_cidoc_pyutils-1.12.1.dist-info/licenses/LICENSE
acdh_cidoc_pyutils-1.12.1.dist-info/RECORD
