Metadata-Version: 2.4
Name: acdh-cidoc-pyutils
Version: 1.12.1
Summary: Helper functions for the generation of CIDOC CRMish RDF (from XML/TEI data)
License-File: LICENSE
Requires-Python: >=3.10
Requires-Dist: acdh-arche-assets>=3.25.0
Requires-Dist: acdh-tei-pyutils>=1.6
Requires-Dist: rdflib>=7.5.0
